<?xml version="1.0" ?>
<?xml-stylesheet type="text/xsl" href="DEFAULT_MEASUREMENT_STYLE.XSL"?>
<Data_Table>
	<Data_Description>
		<Current>
			Current in Amps
		</Current>
		<Index>
			Order in which the point was taken
		</Index>
		<Instrument_Description>
			C:/Users/sandersa/Desktop/My Documents/Share/pyMeasure/Instruments/KEITHLEY6487_NSOM.xml
		</Instrument_Description>
		<Voltage>
			Voltage in Volts
		</Voltage>
		<Date>
			2013-05-09T22:56:01.023000
		</Date>
		<Notes>
			First IV From Top Pt contact, Image 006
		</Notes>
		<Resistance>
			1906534.49635
		</Resistance>
		<Name>
			I 4-8 Wire A
		</Name>
	</Data_Description>
	<Data>
		<Tuple Current="+1.385423E-09" Index="0" Voltage="+000.0000"/>
		<Tuple Current="+1.230239E-09" Index="1" Voltage="-000.2020"/>
		<Tuple Current="+1.010594E-09" Index="2" Voltage="-000.4040"/>
		<Tuple Current="+4.063688E-10" Index="3" Voltage="-000.6060"/>
		<Tuple Current="-7.384351E-10" Index="4" Voltage="-000.8080"/>
		<Tuple Current="-2.511620E-09" Index="5" Voltage="-001.0100"/>
		<Tuple Current="-4.591184E-09" Index="6" Voltage="-001.2120"/>
		<Tuple Current="-6.755967E-09" Index="7" Voltage="-001.4140"/>
		<Tuple Current="-6.475812E-09" Index="8" Voltage="-001.6160"/>
		<Tuple Current="-6.419025E-09" Index="9" Voltage="-001.8180"/>
		<Tuple Current="-4.907096E-09" Index="10" Voltage="-002.0200"/>
		<Tuple Current="-5.774297E-09" Index="11" Voltage="-002.2220"/>
		<Tuple Current="-6.825925E-09" Index="12" Voltage="-002.4240"/>
		<Tuple Current="-7.100283E-09" Index="13" Voltage="-002.6260"/>
		<Tuple Current="-7.674076E-09" Index="14" Voltage="-002.8280"/>
		<Tuple Current="-6.993996E-09" Index="15" Voltage="-003.0300"/>
		<Tuple Current="-6.677941E-09" Index="16" Voltage="-003.2320"/>
		<Tuple Current="-6.792907E-09" Index="17" Voltage="-003.4340"/>
		<Tuple Current="-7.510322E-09" Index="18" Voltage="-003.6360"/>
		<Tuple Current="-8.093380E-09" Index="19" Voltage="-003.8380"/>
		<Tuple Current="-8.253675E-09" Index="20" Voltage="-004.0400"/>
		<Tuple Current="-7.426485E-09" Index="21" Voltage="-004.2420"/>
		<Tuple Current="-7.890145E-09" Index="22" Voltage="-004.4440"/>
		<Tuple Current="-8.177081E-09" Index="23" Voltage="-004.6460"/>
		<Tuple Current="-8.960898E-09" Index="24" Voltage="-004.8480"/>
		<Tuple Current="-8.183680E-09" Index="25" Voltage="-005.0510"/>
		<Tuple Current="-7.666522E-09" Index="26" Voltage="-005.2530"/>
		<Tuple Current="-7.821600E-09" Index="27" Voltage="-005.4550"/>
		<Tuple Current="-7.844282E-09" Index="28" Voltage="-005.6570"/>
		<Tuple Current="-8.336367E-09" Index="29" Voltage="-005.8590"/>
		<Tuple Current="-7.503522E-09" Index="30" Voltage="-006.0610"/>
		<Tuple Current="-7.526634E-09" Index="31" Voltage="-006.2630"/>
		<Tuple Current="-8.212528E-09" Index="32" Voltage="-006.4650"/>
		<Tuple Current="-8.518418E-09" Index="33" Voltage="-006.6670"/>
		<Tuple Current="-8.303618E-09" Index="34" Voltage="-006.8690"/>
		<Tuple Current="-8.728819E-09" Index="35" Voltage="-007.0710"/>
		<Tuple Current="-9.203703E-09" Index="36" Voltage="-007.2730"/>
		<Tuple Current="-9.115139E-09" Index="37" Voltage="-007.4750"/>
		<Tuple Current="-8.977994E-09" Index="38" Voltage="-007.6770"/>
		<Tuple Current="-8.338264E-09" Index="39" Voltage="-007.8790"/>
		<Tuple Current="-8.144831E-09" Index="40" Voltage="-008.0810"/>
		<Tuple Current="-8.195554E-09" Index="41" Voltage="-008.2830"/>
		<Tuple Current="-8.497017E-09" Index="42" Voltage="-008.4850"/>
		<Tuple Current="-8.521252E-09" Index="43" Voltage="-008.6870"/>
		<Tuple Current="-8.597145E-09" Index="44" Voltage="-008.8890"/>
		<Tuple Current="-9.232786E-09" Index="45" Voltage="-009.0910"/>
		<Tuple Current="-8.521343E-09" Index="46" Voltage="-009.2930"/>
		<Tuple Current="-7.653317E-09" Index="47" Voltage="-009.4950"/>
		<Tuple Current="-7.620544E-09" Index="48" Voltage="-009.6970"/>
		<Tuple Current="-7.868764E-09" Index="49" Voltage="-009.8990"/>
		<Tuple Current="-7.889464E-09" Index="50" Voltage="-010.1010"/>
		<Tuple Current="-7.476379E-09" Index="51" Voltage="-010.3030"/>
		<Tuple Current="-7.637290E-09" Index="52" Voltage="-010.5050"/>
		<Tuple Current="-7.675463E-09" Index="53" Voltage="-010.7070"/>
		<Tuple Current="-6.836170E-09" Index="54" Voltage="-010.9090"/>
		<Tuple Current="-7.368043E-09" Index="55" Voltage="-011.1110"/>
		<Tuple Current="-7.856197E-09" Index="56" Voltage="-011.3130"/>
		<Tuple Current="-8.715812E-09" Index="57" Voltage="-011.5150"/>
		<Tuple Current="-1.007125E-08" Index="58" Voltage="-011.7170"/>
		<Tuple Current="-9.682728E-09" Index="59" Voltage="-011.9190"/>
		<Tuple Current="-9.598285E-09" Index="60" Voltage="-012.1210"/>
		<Tuple Current="-8.244589E-09" Index="61" Voltage="-012.3230"/>
		<Tuple Current="-8.517943E-09" Index="62" Voltage="-012.5250"/>
		<Tuple Current="-7.869448E-09" Index="63" Voltage="-012.7270"/>
		<Tuple Current="-8.429442E-09" Index="64" Voltage="-012.9290"/>
		<Tuple Current="-8.522171E-09" Index="65" Voltage="-013.1310"/>
		<Tuple Current="-7.414997E-09" Index="66" Voltage="-013.3330"/>
		<Tuple Current="-8.360864E-09" Index="67" Voltage="-013.5350"/>
		<Tuple Current="-8.057543E-09" Index="68" Voltage="-013.7370"/>
		<Tuple Current="-8.321154E-09" Index="69" Voltage="-013.9390"/>
		<Tuple Current="-7.518325E-09" Index="70" Voltage="-014.1410"/>
		<Tuple Current="-7.808886E-09" Index="71" Voltage="-014.3430"/>
		<Tuple Current="-7.948658E-09" Index="72" Voltage="-014.5450"/>
		<Tuple Current="-8.148030E-09" Index="73" Voltage="-014.7470"/>
		<Tuple Current="-7.798262E-09" Index="74" Voltage="-014.9490"/>
		<Tuple Current="-7.792075E-09" Index="75" Voltage="-015.1520"/>
		<Tuple Current="-7.389126E-09" Index="76" Voltage="-015.3540"/>
		<Tuple Current="-7.622771E-09" Index="77" Voltage="-015.5560"/>
		<Tuple Current="-7.994189E-09" Index="78" Voltage="-015.7580"/>
		<Tuple Current="-6.766184E-09" Index="79" Voltage="-015.9600"/>
		<Tuple Current="-8.000260E-09" Index="80" Voltage="-016.1620"/>
		<Tuple Current="-7.671549E-09" Index="81" Voltage="-016.3640"/>
		<Tuple Current="-8.345938E-09" Index="82" Voltage="-016.5660"/>
		<Tuple Current="-8.342013E-09" Index="83" Voltage="-016.7680"/>
		<Tuple Current="-8.122185E-09" Index="84" Voltage="-016.9700"/>
		<Tuple Current="-7.934305E-09" Index="85" Voltage="-017.1720"/>
		<Tuple Current="-8.230375E-09" Index="86" Voltage="-017.3740"/>
		<Tuple Current="-8.023567E-09" Index="87" Voltage="-017.5760"/>
		<Tuple Current="-7.764630E-09" Index="88" Voltage="-017.7780"/>
		<Tuple Current="-8.165970E-09" Index="89" Voltage="-017.9800"/>
		<Tuple Current="-9.325770E-09" Index="90" Voltage="-018.1820"/>
		<Tuple Current="-8.492286E-09" Index="91" Voltage="-018.3840"/>
		<Tuple Current="-7.814616E-09" Index="92" Voltage="-018.5860"/>
		<Tuple Current="-8.253408E-09" Index="93" Voltage="-018.7880"/>
		<Tuple Current="-7.586903E-09" Index="94" Voltage="-018.9900"/>
		<Tuple Current="-6.572711E-09" Index="95" Voltage="-019.1920"/>
		<Tuple Current="-6.526347E-09" Index="96" Voltage="-019.3940"/>
		<Tuple Current="-6.628404E-09" Index="97" Voltage="-019.5960"/>
		<Tuple Current="-6.376178E-09" Index="98" Voltage="-019.7980"/>
		<Tuple Current="-6.999699E-09" Index="99" Voltage="-020.0000"/>
		<Tuple Current="-6.625327E-09" Index="100" Voltage="-020.0000"/>
		<Tuple Current="-6.471191E-09" Index="101" Voltage="-019.7980"/>
		<Tuple Current="-6.889052E-09" Index="102" Voltage="-019.5960"/>
		<Tuple Current="-7.045451E-09" Index="103" Voltage="-019.3940"/>
		<Tuple Current="-7.416228E-09" Index="104" Voltage="-019.1920"/>
		<Tuple Current="-7.841678E-09" Index="105" Voltage="-018.9900"/>
		<Tuple Current="-7.165323E-09" Index="106" Voltage="-018.7880"/>
		<Tuple Current="-7.235459E-09" Index="107" Voltage="-018.5860"/>
		<Tuple Current="-7.216553E-09" Index="108" Voltage="-018.3840"/>
		<Tuple Current="-7.247677E-09" Index="109" Voltage="-018.1820"/>
		<Tuple Current="-7.766635E-09" Index="110" Voltage="-017.9800"/>
		<Tuple Current="-8.075649E-09" Index="111" Voltage="-017.7780"/>
		<Tuple Current="-7.590375E-09" Index="112" Voltage="-017.5760"/>
		<Tuple Current="-7.675199E-09" Index="113" Voltage="-017.3740"/>
		<Tuple Current="-7.943584E-09" Index="114" Voltage="-017.1720"/>
		<Tuple Current="-7.671518E-09" Index="115" Voltage="-016.9700"/>
		<Tuple Current="-8.181949E-09" Index="116" Voltage="-016.7680"/>
		<Tuple Current="-7.992880E-09" Index="117" Voltage="-016.5660"/>
		<Tuple Current="-7.691615E-09" Index="118" Voltage="-016.3640"/>
		<Tuple Current="-8.102551E-09" Index="119" Voltage="-016.1620"/>
		<Tuple Current="-6.937369E-09" Index="120" Voltage="-015.9600"/>
		<Tuple Current="-7.706950E-09" Index="121" Voltage="-015.7580"/>
		<Tuple Current="-7.710083E-09" Index="122" Voltage="-015.5560"/>
		<Tuple Current="-7.480945E-09" Index="123" Voltage="-015.3540"/>
		<Tuple Current="-7.142349E-09" Index="124" Voltage="-015.1520"/>
		<Tuple Current="-7.108639E-09" Index="125" Voltage="-014.9490"/>
		<Tuple Current="-6.594989E-09" Index="126" Voltage="-014.7470"/>
		<Tuple Current="-6.347610E-09" Index="127" Voltage="-014.5450"/>
		<Tuple Current="-6.492116E-09" Index="128" Voltage="-014.3430"/>
		<Tuple Current="-6.132683E-09" Index="129" Voltage="-014.1410"/>
		<Tuple Current="-6.765383E-09" Index="130" Voltage="-013.9390"/>
		<Tuple Current="-6.571839E-09" Index="131" Voltage="-013.7370"/>
		<Tuple Current="-6.328260E-09" Index="132" Voltage="-013.5350"/>
		<Tuple Current="-6.283781E-09" Index="133" Voltage="-013.3330"/>
		<Tuple Current="-6.754989E-09" Index="134" Voltage="-013.1310"/>
		<Tuple Current="-7.497708E-09" Index="135" Voltage="-012.9290"/>
		<Tuple Current="-7.605191E-09" Index="136" Voltage="-012.7270"/>
		<Tuple Current="-7.590696E-09" Index="137" Voltage="-012.5250"/>
		<Tuple Current="-6.551670E-09" Index="138" Voltage="-012.3230"/>
		<Tuple Current="-6.936850E-09" Index="139" Voltage="-012.1210"/>
		<Tuple Current="-7.568997E-09" Index="140" Voltage="-011.9190"/>
		<Tuple Current="-6.461916E-09" Index="141" Voltage="-011.7170"/>
		<Tuple Current="-7.142225E-09" Index="142" Voltage="-011.5150"/>
		<Tuple Current="-7.172003E-09" Index="143" Voltage="-011.3130"/>
		<Tuple Current="-7.137100E-09" Index="144" Voltage="-011.1110"/>
		<Tuple Current="-6.908587E-09" Index="145" Voltage="-010.9090"/>
		<Tuple Current="-7.462297E-09" Index="146" Voltage="-010.7070"/>
		<Tuple Current="-8.465165E-09" Index="147" Voltage="-010.5050"/>
		<Tuple Current="-7.004015E-09" Index="148" Voltage="-010.3030"/>
		<Tuple Current="-6.888095E-09" Index="149" Voltage="-010.1010"/>
		<Tuple Current="-6.725015E-09" Index="150" Voltage="-009.8990"/>
		<Tuple Current="-7.091645E-09" Index="151" Voltage="-009.6970"/>
		<Tuple Current="-6.701223E-09" Index="152" Voltage="-009.4950"/>
		<Tuple Current="-6.864637E-09" Index="153" Voltage="-009.2930"/>
		<Tuple Current="-6.566079E-09" Index="154" Voltage="-009.0910"/>
		<Tuple Current="-6.311672E-09" Index="155" Voltage="-008.8890"/>
		<Tuple Current="-6.396133E-09" Index="156" Voltage="-008.6870"/>
		<Tuple Current="-6.307634E-09" Index="157" Voltage="-008.4850"/>
		<Tuple Current="-7.093455E-09" Index="158" Voltage="-008.2830"/>
		<Tuple Current="-7.612913E-09" Index="159" Voltage="-008.0810"/>
		<Tuple Current="-7.028766E-09" Index="160" Voltage="-007.8790"/>
		<Tuple Current="-6.501249E-09" Index="161" Voltage="-007.6770"/>
		<Tuple Current="-7.387258E-09" Index="162" Voltage="-007.4750"/>
		<Tuple Current="-8.139971E-09" Index="163" Voltage="-007.2730"/>
		<Tuple Current="-8.158024E-09" Index="164" Voltage="-007.0710"/>
		<Tuple Current="-7.803433E-09" Index="165" Voltage="-006.8690"/>
		<Tuple Current="-7.256513E-09" Index="166" Voltage="-006.6670"/>
		<Tuple Current="-5.998131E-09" Index="167" Voltage="-006.4650"/>
		<Tuple Current="-6.265189E-09" Index="168" Voltage="-006.2630"/>
		<Tuple Current="-6.247856E-09" Index="169" Voltage="-006.0610"/>
		<Tuple Current="-5.688349E-09" Index="170" Voltage="-005.8590"/>
		<Tuple Current="-5.726718E-09" Index="171" Voltage="-005.6570"/>
		<Tuple Current="-6.074840E-09" Index="172" Voltage="-005.4550"/>
		<Tuple Current="-6.142574E-09" Index="173" Voltage="-005.2530"/>
		<Tuple Current="-5.797550E-09" Index="174" Voltage="-005.0510"/>
		<Tuple Current="-6.013480E-09" Index="175" Voltage="-004.8480"/>
		<Tuple Current="-6.073225E-09" Index="176" Voltage="-004.6460"/>
		<Tuple Current="-6.011422E-09" Index="177" Voltage="-004.4440"/>
		<Tuple Current="-5.817319E-09" Index="178" Voltage="-004.2420"/>
		<Tuple Current="-5.751239E-09" Index="179" Voltage="-004.0400"/>
		<Tuple Current="-5.682778E-09" Index="180" Voltage="-003.8380"/>
		<Tuple Current="-5.109034E-09" Index="181" Voltage="-003.6360"/>
		<Tuple Current="-5.817190E-09" Index="182" Voltage="-003.4340"/>
		<Tuple Current="-5.444002E-09" Index="183" Voltage="-003.2320"/>
		<Tuple Current="-4.882744E-09" Index="184" Voltage="-003.0300"/>
		<Tuple Current="-5.178154E-09" Index="185" Voltage="-002.8280"/>
		<Tuple Current="-5.047180E-09" Index="186" Voltage="-002.6260"/>
		<Tuple Current="-5.728285E-09" Index="187" Voltage="-002.4240"/>
		<Tuple Current="-5.277775E-09" Index="188" Voltage="-002.2220"/>
		<Tuple Current="-4.341843E-09" Index="189" Voltage="-002.0200"/>
		<Tuple Current="-3.299935E-09" Index="190" Voltage="-001.8180"/>
		<Tuple Current="-2.091639E-09" Index="191" Voltage="-001.6160"/>
		<Tuple Current="-1.394267E-09" Index="192" Voltage="-001.4140"/>
		<Tuple Current="-6.082450E-10" Index="193" Voltage="-001.2120"/>
		<Tuple Current="+2.255773E-10" Index="194" Voltage="-001.0100"/>
		<Tuple Current="+6.971029E-10" Index="195" Voltage="-000.8080"/>
		<Tuple Current="+9.513855E-10" Index="196" Voltage="-000.6060"/>
		<Tuple Current="+1.203989E-09" Index="197" Voltage="-000.4040"/>
		<Tuple Current="+1.279833E-09" Index="198" Voltage="-000.2020"/>
		<Tuple Current="+1.407045E-09" Index="199" Voltage="+000.0000"/>
		<Tuple Current="+1.398555E-09" Index="200" Voltage="+000.0000"/>
		<Tuple Current="+1.570618E-09" Index="201" Voltage="+000.2020"/>
		<Tuple Current="+1.892612E-09" Index="202" Voltage="+000.4040"/>
		<Tuple Current="+2.419563E-09" Index="203" Voltage="+000.6060"/>
		<Tuple Current="+3.006908E-09" Index="204" Voltage="+000.8080"/>
		<Tuple Current="+3.800328E-09" Index="205" Voltage="+001.0100"/>
		<Tuple Current="+5.440262E-09" Index="206" Voltage="+001.2120"/>
		<Tuple Current="+8.471416E-09" Index="207" Voltage="+001.4140"/>
		<Tuple Current="+8.587690E-09" Index="208" Voltage="+001.6160"/>
		<Tuple Current="+1.177304E-08" Index="209" Voltage="+001.8180"/>
		<Tuple Current="+1.652304E-08" Index="210" Voltage="+002.0200"/>
		<Tuple Current="+2.212618E-08" Index="211" Voltage="+002.2220"/>
		<Tuple Current="+3.140675E-08" Index="212" Voltage="+002.4240"/>
		<Tuple Current="+3.681302E-08" Index="213" Voltage="+002.6260"/>
		<Tuple Current="+6.564208E-08" Index="214" Voltage="+002.8280"/>
		<Tuple Current="+2.625216E-07" Index="215" Voltage="+003.0300"/>
		<Tuple Current="+2.382865E-07" Index="216" Voltage="+003.2320"/>
		<Tuple Current="+2.822760E-07" Index="217" Voltage="+003.4340"/>
		<Tuple Current="+5.179850E-07" Index="218" Voltage="+003.6360"/>
		<Tuple Current="+8.103369E-07" Index="219" Voltage="+003.8380"/>
		<Tuple Current="+9.624421E-07" Index="220" Voltage="+004.0400"/>
		<Tuple Current="+1.020777E-06" Index="221" Voltage="+004.2420"/>
		<Tuple Current="+1.113597E-06" Index="222" Voltage="+004.4440"/>
		<Tuple Current="+1.134173E-06" Index="223" Voltage="+004.6460"/>
		<Tuple Current="+1.270390E-06" Index="224" Voltage="+004.8480"/>
		<Tuple Current="+1.343004E-06" Index="225" Voltage="+005.0510"/>
		<Tuple Current="+3.750757E-06" Index="226" Voltage="+005.2530"/>
		<Tuple Current="+3.792756E-06" Index="227" Voltage="+005.4550"/>
		<Tuple Current="+2.453482E-06" Index="228" Voltage="+005.6570"/>
		<Tuple Current="+2.589522E-06" Index="229" Voltage="+005.8590"/>
		<Tuple Current="+2.672850E-06" Index="230" Voltage="+006.0610"/>
		<Tuple Current="+3.378070E-06" Index="231" Voltage="+006.2630"/>
		<Tuple Current="+3.671176E-06" Index="232" Voltage="+006.4650"/>
		<Tuple Current="+4.571826E-06" Index="233" Voltage="+006.6670"/>
		<Tuple Current="+3.537673E-06" Index="234" Voltage="+006.8690"/>
		<Tuple Current="+3.752295E-06" Index="235" Voltage="+007.0710"/>
		<Tuple Current="+5.749452E-06" Index="236" Voltage="+007.2730"/>
		<Tuple Current="+5.770225E-06" Index="237" Voltage="+007.4750"/>
		<Tuple Current="+6.096949E-06" Index="238" Voltage="+007.6770"/>
		<Tuple Current="+6.352760E-06" Index="239" Voltage="+007.8790"/>
		<Tuple Current="+4.662887E-06" Index="240" Voltage="+008.0810"/>
		<Tuple Current="+5.726406E-06" Index="241" Voltage="+008.2830"/>
		<Tuple Current="+6.231264E-06" Index="242" Voltage="+008.4850"/>
		<Tuple Current="+6.681710E-06" Index="243" Voltage="+008.6870"/>
		<Tuple Current="+6.896840E-06" Index="244" Voltage="+008.8890"/>
		<Tuple Current="+7.125235E-06" Index="245" Voltage="+009.0910"/>
		<Tuple Current="+7.663752E-06" Index="246" Voltage="+009.2930"/>
		<Tuple Current="+7.706453E-06" Index="247" Voltage="+009.4950"/>
		<Tuple Current="+8.018280E-06" Index="248" Voltage="+009.6970"/>
		<Tuple Current="+8.122338E-06" Index="249" Voltage="+009.8990"/>
		<Tuple Current="+8.186134E-06" Index="250" Voltage="+010.1010"/>
		<Tuple Current="+9.092950E-06" Index="251" Voltage="+010.3030"/>
		<Tuple Current="+9.155152E-06" Index="252" Voltage="+010.5050"/>
		<Tuple Current="+9.463504E-06" Index="253" Voltage="+010.7070"/>
		<Tuple Current="+1.011741E-05" Index="254" Voltage="+010.9090"/>
		<Tuple Current="+1.039034E-05" Index="255" Voltage="+011.1110"/>
		<Tuple Current="+1.067111E-05" Index="256" Voltage="+011.3130"/>
		<Tuple Current="+1.095032E-05" Index="257" Voltage="+011.5150"/>
		<Tuple Current="+1.116992E-05" Index="258" Voltage="+011.7170"/>
		<Tuple Current="+1.142372E-05" Index="259" Voltage="+011.9190"/>
		<Tuple Current="+1.148594E-05" Index="260" Voltage="+012.1210"/>
		<Tuple Current="+1.186253E-05" Index="261" Voltage="+012.3230"/>
		<Tuple Current="+1.229833E-05" Index="262" Voltage="+012.5250"/>
		<Tuple Current="+1.243442E-05" Index="263" Voltage="+012.7270"/>
		<Tuple Current="+1.279593E-05" Index="264" Voltage="+012.9290"/>
		<Tuple Current="+1.290443E-05" Index="265" Voltage="+013.1310"/>
		<Tuple Current="+1.301409E-05" Index="266" Voltage="+013.3330"/>
		<Tuple Current="+1.358635E-05" Index="267" Voltage="+013.5350"/>
		<Tuple Current="+1.403749E-05" Index="268" Voltage="+013.7370"/>
		<Tuple Current="+1.404877E-05" Index="269" Voltage="+013.9390"/>
		<Tuple Current="+1.466454E-05" Index="270" Voltage="+014.1410"/>
		<Tuple Current="+1.472434E-05" Index="271" Voltage="+014.3430"/>
		<Tuple Current="+1.514424E-05" Index="272" Voltage="+014.5450"/>
		<Tuple Current="+1.549038E-05" Index="273" Voltage="+014.7470"/>
		<Tuple Current="+1.599446E-05" Index="274" Voltage="+014.9490"/>
		<Tuple Current="+1.619341E-05" Index="275" Voltage="+015.1520"/>
		<Tuple Current="+1.631562E-05" Index="276" Voltage="+015.3540"/>
		<Tuple Current="+1.675033E-05" Index="277" Voltage="+015.5560"/>
		<Tuple Current="+1.734073E-05" Index="278" Voltage="+015.7580"/>
		<Tuple Current="+1.750069E-05" Index="279" Voltage="+015.9600"/>
		<Tuple Current="+1.782061E-05" Index="280" Voltage="+016.1620"/>
		<Tuple Current="+1.826752E-05" Index="281" Voltage="+016.3640"/>
		<Tuple Current="+1.850611E-05" Index="282" Voltage="+016.5660"/>
		<Tuple Current="+1.891751E-05" Index="283" Voltage="+016.7680"/>
		<Tuple Current="+1.932068E-05" Index="284" Voltage="+016.9700"/>
		<Tuple Current="+1.953222E-05" Index="285" Voltage="+017.1720"/>
		<Tuple Current="+1.974866E-05" Index="286" Voltage="+017.3740"/>
		<Tuple Current="+2.020854E-05" Index="287" Voltage="+017.5760"/>
		<Tuple Current="+2.069885E-05" Index="288" Voltage="+017.7780"/>
		<Tuple Current="+2.087293E-05" Index="289" Voltage="+017.9800"/>
		<Tuple Current="+2.116203E-05" Index="290" Voltage="+018.1820"/>
		<Tuple Current="+2.139574E-05" Index="291" Voltage="+018.3840"/>
		<Tuple Current="+2.174395E-05" Index="292" Voltage="+018.5860"/>
		<Tuple Current="+2.205674E-05" Index="293" Voltage="+018.7880"/>
		<Tuple Current="+2.237734E-05" Index="294" Voltage="+018.9900"/>
		<Tuple Current="+2.275976E-05" Index="295" Voltage="+019.1920"/>
		<Tuple Current="+2.310877E-05" Index="296" Voltage="+019.3940"/>
		<Tuple Current="+2.357930E-05" Index="297" Voltage="+019.5960"/>
		<Tuple Current="+2.393049E-05" Index="298" Voltage="+019.7980"/>
		<Tuple Current="+2.391408E-05" Index="299" Voltage="+020.0000"/>
		<Tuple Current="+2.412863E-05" Index="300" Voltage="+020.0000"/>
		<Tuple Current="+2.364315E-05" Index="301" Voltage="+019.7980"/>
		<Tuple Current="+2.340352E-05" Index="302" Voltage="+019.5960"/>
		<Tuple Current="+2.330405E-05" Index="303" Voltage="+019.3940"/>
		<Tuple Current="+2.289113E-05" Index="304" Voltage="+019.1920"/>
		<Tuple Current="+2.256023E-05" Index="305" Voltage="+018.9900"/>
		<Tuple Current="+2.205296E-05" Index="306" Voltage="+018.7880"/>
		<Tuple Current="+2.185085E-05" Index="307" Voltage="+018.5860"/>
		<Tuple Current="+2.151153E-05" Index="308" Voltage="+018.3840"/>
		<Tuple Current="+2.142640E-05" Index="309" Voltage="+018.1820"/>
		<Tuple Current="+2.119909E-05" Index="310" Voltage="+017.9800"/>
		<Tuple Current="+2.086932E-05" Index="311" Voltage="+017.7780"/>
		<Tuple Current="+2.056796E-05" Index="312" Voltage="+017.5760"/>
		<Tuple Current="+2.003214E-05" Index="313" Voltage="+017.3740"/>
		<Tuple Current="+1.953659E-05" Index="314" Voltage="+017.1720"/>
		<Tuple Current="+1.931834E-05" Index="315" Voltage="+016.9700"/>
		<Tuple Current="+1.910783E-05" Index="316" Voltage="+016.7680"/>
		<Tuple Current="+1.874527E-05" Index="317" Voltage="+016.5660"/>
		<Tuple Current="+1.817917E-05" Index="318" Voltage="+016.3640"/>
		<Tuple Current="+1.796164E-05" Index="319" Voltage="+016.1620"/>
		<Tuple Current="+1.770376E-05" Index="320" Voltage="+015.9600"/>
		<Tuple Current="+1.739275E-05" Index="321" Voltage="+015.7580"/>
		<Tuple Current="+1.697888E-05" Index="322" Voltage="+015.5560"/>
		<Tuple Current="+1.673568E-05" Index="323" Voltage="+015.3540"/>
		<Tuple Current="+1.649738E-05" Index="324" Voltage="+015.1520"/>
		<Tuple Current="+1.616286E-05" Index="325" Voltage="+014.9490"/>
		<Tuple Current="+1.578198E-05" Index="326" Voltage="+014.7470"/>
		<Tuple Current="+1.557016E-05" Index="327" Voltage="+014.5450"/>
		<Tuple Current="+1.528673E-05" Index="328" Voltage="+014.3430"/>
		<Tuple Current="+1.495372E-05" Index="329" Voltage="+014.1410"/>
		<Tuple Current="+1.459450E-05" Index="330" Voltage="+013.9390"/>
		<Tuple Current="+1.388371E-05" Index="331" Voltage="+013.7370"/>
		<Tuple Current="+1.365244E-05" Index="332" Voltage="+013.5350"/>
		<Tuple Current="+1.342387E-05" Index="333" Voltage="+013.3330"/>
		<Tuple Current="+1.316507E-05" Index="334" Voltage="+013.1310"/>
		<Tuple Current="+1.292115E-05" Index="335" Voltage="+012.9290"/>
		<Tuple Current="+1.264828E-05" Index="336" Voltage="+012.7270"/>
		<Tuple Current="+1.236896E-05" Index="337" Voltage="+012.5250"/>
		<Tuple Current="+1.213579E-05" Index="338" Voltage="+012.3230"/>
		<Tuple Current="+1.187942E-05" Index="339" Voltage="+012.1210"/>
		<Tuple Current="+1.157883E-05" Index="340" Voltage="+011.9190"/>
		<Tuple Current="+1.140195E-05" Index="341" Voltage="+011.7170"/>
		<Tuple Current="+1.107077E-05" Index="342" Voltage="+011.5150"/>
		<Tuple Current="+1.074310E-05" Index="343" Voltage="+011.3130"/>
		<Tuple Current="+1.053101E-05" Index="344" Voltage="+011.1110"/>
		<Tuple Current="+1.027260E-05" Index="345" Voltage="+010.9090"/>
		<Tuple Current="+9.890997E-06" Index="346" Voltage="+010.7070"/>
		<Tuple Current="+9.655176E-06" Index="347" Voltage="+010.5050"/>
		<Tuple Current="+9.459944E-06" Index="348" Voltage="+010.3030"/>
		<Tuple Current="+9.167617E-06" Index="349" Voltage="+010.1010"/>
		<Tuple Current="+8.927973E-06" Index="350" Voltage="+009.8990"/>
		<Tuple Current="+8.576731E-06" Index="351" Voltage="+009.6970"/>
		<Tuple Current="+7.968812E-06" Index="352" Voltage="+009.4950"/>
		<Tuple Current="+7.561358E-06" Index="353" Voltage="+009.2930"/>
		<Tuple Current="+7.611161E-06" Index="354" Voltage="+009.0910"/>
		<Tuple Current="+7.585829E-06" Index="355" Voltage="+008.8890"/>
		<Tuple Current="+7.604717E-06" Index="356" Voltage="+008.6870"/>
		<Tuple Current="+7.435338E-06" Index="357" Voltage="+008.4850"/>
		<Tuple Current="+7.173388E-06" Index="358" Voltage="+008.2830"/>
		<Tuple Current="+6.870849E-06" Index="359" Voltage="+008.0810"/>
		<Tuple Current="+6.665689E-06" Index="360" Voltage="+007.8790"/>
		<Tuple Current="+6.455877E-06" Index="361" Voltage="+007.6770"/>
		<Tuple Current="+6.156252E-06" Index="362" Voltage="+007.4750"/>
		<Tuple Current="+5.761258E-06" Index="363" Voltage="+007.2730"/>
		<Tuple Current="+5.552371E-06" Index="364" Voltage="+007.0710"/>
		<Tuple Current="+4.623207E-06" Index="365" Voltage="+006.8690"/>
		<Tuple Current="+3.789397E-06" Index="366" Voltage="+006.6670"/>
		<Tuple Current="+3.823109E-06" Index="367" Voltage="+006.4650"/>
		<Tuple Current="+4.052763E-06" Index="368" Voltage="+006.2630"/>
		<Tuple Current="+3.907604E-06" Index="369" Voltage="+006.0610"/>
		<Tuple Current="+3.671667E-06" Index="370" Voltage="+005.8590"/>
		<Tuple Current="+2.928943E-06" Index="371" Voltage="+005.6570"/>
		<Tuple Current="+2.717840E-06" Index="372" Voltage="+005.4550"/>
		<Tuple Current="+2.505986E-06" Index="373" Voltage="+005.2530"/>
		<Tuple Current="+2.351135E-06" Index="374" Voltage="+005.0510"/>
		<Tuple Current="+2.192171E-06" Index="375" Voltage="+004.8480"/>
		<Tuple Current="+2.038699E-06" Index="376" Voltage="+004.6460"/>
		<Tuple Current="+1.818106E-06" Index="377" Voltage="+004.4440"/>
		<Tuple Current="+1.760640E-06" Index="378" Voltage="+004.2420"/>
		<Tuple Current="+1.601940E-06" Index="379" Voltage="+004.0400"/>
		<Tuple Current="+1.547495E-06" Index="380" Voltage="+003.8380"/>
		<Tuple Current="+1.293073E-06" Index="381" Voltage="+003.6360"/>
		<Tuple Current="+1.218258E-06" Index="382" Voltage="+003.4340"/>
		<Tuple Current="+1.042640E-06" Index="383" Voltage="+003.2320"/>
		<Tuple Current="+8.989670E-07" Index="384" Voltage="+003.0300"/>
		<Tuple Current="+7.525399E-07" Index="385" Voltage="+002.8280"/>
		<Tuple Current="+6.335453E-07" Index="386" Voltage="+002.6260"/>
		<Tuple Current="+5.314034E-07" Index="387" Voltage="+002.4240"/>
		<Tuple Current="+4.382201E-07" Index="388" Voltage="+002.2220"/>
		<Tuple Current="+3.580436E-07" Index="389" Voltage="+002.0200"/>
		<Tuple Current="+2.784255E-07" Index="390" Voltage="+001.8180"/>
		<Tuple Current="+1.686402E-07" Index="391" Voltage="+001.6160"/>
		<Tuple Current="+1.203095E-07" Index="392" Voltage="+001.4140"/>
		<Tuple Current="+7.830617E-08" Index="393" Voltage="+001.2120"/>
		<Tuple Current="+3.632267E-08" Index="394" Voltage="+001.0100"/>
		<Tuple Current="+2.122912E-08" Index="395" Voltage="+000.8080"/>
		<Tuple Current="+9.338408E-09" Index="396" Voltage="+000.6060"/>
		<Tuple Current="+4.262565E-09" Index="397" Voltage="+000.4040"/>
		<Tuple Current="+2.231216E-09" Index="398" Voltage="+000.2020"/>
		<Tuple Current="+1.382159E-09" Index="399" Voltage="+000.0000"/>
	</Data>
</Data_Table>
